asn_check/__init__.py
asn_check/asn_check.py
asn_check/data.py
asn_check/ip_binary_tree.py
asn_check/rfc6890.py
asn_check/utils.py
asn_check-1.1.3.dist-info/METADATA
asn_check-1.1.3.dist-info/WHEEL
asn_check-1.1.3.dist-info/entry_points.txt
asn_check-1.1.3.dist-info/licenses/LICENSE
asn_check-1.1.3.dist-info/RECORD
