Metadata-Version: 2.3
Name: asn-check
Version: 1.1.3
Summary: Check ASNs and metadata for a list of IPs
Project-URL: Documentation, https://github.com/ArcHound/asn-check#readme
Project-URL: Issues, https://github.com/ArcHound/asn-check/issues
Project-URL: Source, https://github.com/ArcHound/asn-check
Author-email: Miloslav Homer <miloslav.homer@gmail.com>
Keywords: asn-lookup,click,ipv4,ipv6,ripe
Classifier: Development Status :: 5 - Production/Stable
Classifier: Programming Language :: Python
Classifier: Programming Language :: Python :: 3.7
Classifier: Programming Language :: Python :: 3.8
Classifier: Programming Language :: Python :: 3.9
Classifier: Programming Language :: Python :: 3.10
Classifier: Programming Language :: Python :: 3.11
Classifier: Programming Language :: Python :: Implementation :: CPython
Classifier: Programming Language :: Python :: Implementation :: PyPy
Requires-Python: >=3.7
Requires-Dist: click
Requires-Dist: platformdirs
Requires-Dist: requests
